pyddem/__init__.py
pyddem/fit_tools.py
pyddem/spstats_tools.py
pyddem/stack_tools.py
pyddem/tdem_tools.py
pyddem/vector_tools.py
pyddem/volint_tools.py
pyddem-0.1.1.data/scripts/fit_gp_monthly_aster.py
pyddem-0.1.1.data/scripts/fit_stack.py
pyddem-0.1.1.data/scripts/stack_dems.py
pyddem-0.1.1.data/scripts/stack_per_1deg_tiles_aster.py
pyddem-0.1.1.dist-info/LICENSE
pyddem-0.1.1.dist-info/METADATA
pyddem-0.1.1.dist-info/WHEEL
pyddem-0.1.1.dist-info/top_level.txt
pyddem-0.1.1.dist-info/RECORD
